django_business_rules/__init__.py
django_business_rules/admin.py
django_business_rules/apps.py
django_business_rules/business_rule.py
django_business_rules/forms.py
django_business_rules/models.py
django_business_rules/urls.py
django_business_rules/views.py
django_business_rules/management/__init__.py
django_business_rules/management/commands/__init__.py
django_business_rules/management/commands/dbr.py
django_business_rules/migrations/0001_initial.py
django_business_rules/migrations/0002_auto_20180328_1747.py
django_business_rules/migrations/__init__.py
django_business_rules/static/django_business_rules/css/dbr.css
django_business_rules/static/django_business_rules/js/dbr.js
django_business_rules/static/django_business_rules/js/lib/business-rules/actions-builder.js
django_business_rules/static/django_business_rules/js/lib/business-rules/conditions-builder.js
django_business_rules/templates/django_business_rules/business_rule_form.html
django_business_rules/templates/django_business_rules/business_rule_list.html
django_business_rules-1.0.5.dist-info/DESCRIPTION.rst
django_business_rules-1.0.5.dist-info/METADATA
django_business_rules-1.0.5.dist-info/RECORD
django_business_rules-1.0.5.dist-info/WHEEL
django_business_rules-1.0.5.dist-info/metadata.json
django_business_rules-1.0.5.dist-info/top_level.txt
